petfinder/__init__.py
petfinder/client.py
petfinder/models.py
petfinder_client-0.0.2.dist-info/LICENSE
petfinder_client-0.0.2.dist-info/METADATA
petfinder_client-0.0.2.dist-info/WHEEL
petfinder_client-0.0.2.dist-info/top_level.txt
petfinder_client-0.0.2.dist-info/RECORD
